cryptio/__init__.py
cryptio/header.py
cryptio/io.py
cryptio-0.0.1.dev16.dist-info/DESCRIPTION.rst
cryptio-0.0.1.dev16.dist-info/METADATA
cryptio-0.0.1.dev16.dist-info/RECORD
cryptio-0.0.1.dev16.dist-info/WHEEL
cryptio-0.0.1.dev16.dist-info/metadata.json
cryptio-0.0.1.dev16.dist-info/pbr.json
cryptio-0.0.1.dev16.dist-info/top_level.txt
