Metadata-Version: 2.0
Name: cryptio
Version: 0.0.1.dev16
Summary: file-like interface for authenticated encryption
Home-page: http://cryptio.readthedocs.io/
Author: Zack Buhman
Author-email: zack@buhman.org
License: UNKNOWN
Platform: UNKNOWN
Classifier: Development Status :: 5 - Production/Stable
Classifier: Intended Audience :: Developers
Classifier: License :: OSI Approved :: GNU Affero General Public License v3 or later (AGPLv3+)
Classifier: Operating System :: POSIX :: Linux
Classifier: Programming Language :: Python
Classifier: Programming Language :: Python :: 3 :: Only
Classifier: Programming Language :: Python :: 3.4
Classifier: Programming Language :: Python :: 3.5
Classifier: Programming Language :: Python :: 3.6
Requires-Dist: cryptography (>=1.7.2)
Requires-Dist: memoized-property (>=1.0.3)
